titech/CSC.T433.AdvancedComputerArchitecture/final/code2.v
/******************************************************************************/
/* Simple Processor Ver.07                    2018-12-18  ArchLab. TOKYO TECH */
/* Four stage pipelined processor supporting ADD and BNE,
/* which has no data forwarding      */
/******************************************************************************/
`default_nettype none
`timescale 1ns/100ps
/******************************************************************************/
module top();
  reg CLK, RST_X;
  initial begin CLK = 1; forever #50 CLK = ~CLK; end
  initial begin RST_X = 0; #140 RST_X = 1;       end
  initial begin $dumpfile("wave.vcd"); $dumpvars(0, p); end

  initial begin /* initialize the instruction & data memory  & regfile */
    p.imem.mem[0] = {6'h8, 5'd0, 5'd17, 16'd0};
    p.imem.mem[1] = {6'h8, 5'd0, 5'd8, 16'd200};
    p.imem.mem[2] = {6'h0, 5'd0, 5'd0, 5'd9, 5'd0, 6'h20};
    p.imem.mem[3] = {6'h0, 5'd0, 5'd0, 5'd0, 5'd0, 6'h20};
    p.imem.mem[4] = {6'h0, 5'd0, 5'd17, 5'd10, 5'd0, 6'h20};
    p.imem.mem[5] = {6'h0, 5'd0, 5'd0, 5'd0, 5'd0, 6'h20};
    // L1
    p.imem.mem[6] = {6'h4, 5'd8, 5'd9, 16'h8};
    p.imem.mem[7] = {6'h0, 5'd0, 5'd0, 5'd0, 5'd0, 6'h20};
    p.imem.mem[8] = {6'h0, 5'd0, 5'd0, 5'd0, 5'd0, 6'h20};
    p.imem.mem[9] = {6'h2b, 5'd10, 5'd9, 16'h0};
    p.imem.mem[10] = {6'h8, 5'd10, 5'd10, 16'd4};
    p.imem.mem[11] = {6'h8, 5'd9, 5'd9, 16'd1};
    p.imem.mem[12] = {6'h2, 26'h6};
    p.imem.mem[13] = {6'h0, 5'd0, 5'd0, 5'd0, 5'd0, 6'h20};
    p.imem.mem[14] = {6'h0, 5'd0, 5'd0, 5'd0, 5'd0, 6'h20};
    // END1
    p.imem.mem[15] = {6'h0, 5'd0, 5'd17, 5'd10, 5'd0, 6'h20};
    p.imem.mem[16] = {6'h0, 5'd0, 5'd0, 5'd0, 5'd0, 6'h20};
    p.imem.mem[17] = {6'h0, 5'd0, 5'd0, 5'd0, 5'd0, 6'h20};
    p.imem.mem[18] = {6'h0, 5'd0, 5'd0, 5'd0, 5'd0, 6'h20};
    p.imem.mem[19] = {6'h8, 5'd10, 5'd8, 16'd796};
    p.imem.mem[20] = {6'h0, 5'd0, 5'd0, 5'd0, 5'd0, 6'h20};
    p.imem.mem[21] = {6'h0, 5'd0, 5'd0, 5'd0, 5'd0, 6'h20};
    p.imem.mem[22] = {6'h0, 5'd0, 5'd0, 5'd0, 5'd0, 6'h20};
    // L2
    p.imem.mem[23] = {6'h4, 5'd8, 5'd10, 16'd16};
    p.imem.mem[24] = {6'h0, 5'd0, 5'd0, 5'd0, 5'd0, 6'h20};
    p.imem.mem[25] = {6'h0, 5'd0, 5'd0, 5'd0, 5'd0, 6'h20};
    p.imem.mem[26] = {6'h23, 5'd10, 5'd11, 16'h0};
    p.imem.mem[27] = {6'h23, 5'd10, 5'd12, 16'h4};
    p.imem.mem[28] = {6'h0, 5'd0, 5'd0, 5'd0, 5'd0, 6'h20};
    p.imem.mem[29] = {6'h0, 5'd0, 5'd0, 5'd0, 5'd0, 6'h20};
    p.imem.mem[30] = {6'h0, 5'd0, 5'd0, 5'd0, 5'd0, 6'h20};
    p.imem.mem[31] = {6'h0, 5'd11, 5'd12, 5'd11, 5'd0, 6'h20};
    p.imem.mem[32] = {6'h0, 5'd0, 5'd0, 5'd0, 5'd0, 6'h20};
    p.imem.mem[33] = {6'h0, 5'd0, 5'd0, 5'd0, 5'd0, 6'h20};
    p.imem.mem[34] = {6'h0, 5'd0, 5'd0, 5'd0, 5'd0, 6'h20};
    p.imem.mem[35] = {6'h2b, 5'd10, 5'd11, 16'h4};
    p.imem.mem[36] = {6'h8, 5'd10, 5'd10, 16'd4};
    p.imem.mem[37] = {6'h2, 26'd23};
    p.imem.mem[38] = {6'h0, 5'd0, 5'd0, 5'd0, 5'd0, 6'h20};
    p.imem.mem[39] = {6'h0, 5'd0, 5'd0, 5'd0, 5'd0, 6'h20};
    // END2
    p.imem.mem[40] = {6'h0, 5'd0, 5'd17, 5'd10, 5'd0, 6'h20};
    p.imem.mem[41] = {6'h8, 5'd10, 5'd8, 16'd800};
    p.imem.mem[42] = {6'h0, 5'd0, 5'd0, 5'd16, 5'd0, 6'h20};
    p.imem.mem[43] = {6'h0, 5'd0, 5'd0, 5'd0, 5'd0, 6'h20};
    p.imem.mem[44] = {6'h0, 5'd0, 5'd0, 5'd0, 5'd0, 6'h20};
    p.imem.mem[45] = {6'h0, 5'd0, 5'd0, 5'd0, 5'd0, 6'h20};
    // L3
    p.imem.mem[46] = {6'h4, 5'd8, 5'd10, 16'd11};
    p.imem.mem[47] = {6'h0, 5'd0, 5'd0, 5'd0, 5'd0, 6'h20};
    p.imem.mem[48] = {6'h0, 5'd0, 5'd0, 5'd0, 5'd0, 6'h20};
    p.imem.mem[49] = {6'h23, 5'd10, 5'd11, 16'h0};
    p.imem.mem[50] = {6'h0, 5'd0, 5'd0, 5'd0, 5'd0, 6'h20};
    p.imem.mem[51] = {6'h0, 5'd0, 5'd0, 5'd0, 5'd0, 6'h20};
    p.imem.mem[52] = {6'h0, 5'd0, 5'd0, 5'd0, 5'd0, 6'h20};
    p.imem.mem[53] = {6'h0, 5'd16, 5'd11, 5'd16, 5'd0, 6'h20};
    p.imem.mem[54] = {6'h8, 5'd10, 5'd10, 16'd4};
    p.imem.mem[55] = {6'h2, 26'd46};
    p.imem.mem[56] = {6'h0, 5'd0, 5'd0, 5'd0, 5'd0, 6'h20};
    p.imem.mem[57] = {6'h0, 5'd0, 5'd0, 5'd0, 5'd0, 6'h20};
    // END3
    p.imem.mem[58] = {6'h0, 5'd16, 5'd0, 5'd16, 5'd0, 6'h20}; // show s0
  end
  initial #30000 $finish();

  PROCESSOR_07 p(CLK, RST_X);
endmodule

/******************************************************************************/
module PROCESSOR_07(CLK, RST_X);
  input wire CLK, RST_X;

  /***************************************** IF Stage  **********************/
  reg  [31:0] PC;
  wire [31:0] #20 If_NPC = PC + 4;
  always @(posedge CLK) PC <= #5 (!RST_X) ? 0 : (Ex_TKN) ? IdEx_TPC : If_NPC;

  wire [31:0] If_IR;
  MEM imem(CLK, PC, 32'd0, 1'd0, If_IR);

  reg [31:0] IfId_IR, IfId_PC, IfId_NPC;
  always @(posedge CLK) IfId_IR  <= #5 (!RST_X) ? 0 : If_IR;
  always @(posedge CLK) IfId_PC  <= #5 (!RST_X) ? 0 : PC;
  always @(posedge CLK) IfId_NPC <= #5 (!RST_X) ? 0 : If_NPC;
  /***************************************** ID Stage  **********************/
  wire [5:0]  #10 Id_OP = IfId_IR[31:26];
  wire [4:0]  #10 Id_RS = IfId_IR[25:21];
  wire [4:0]  #10 Id_RT = IfId_IR[20:16];
  wire [4:0]  #10 Id_RD = IfId_IR[15:11];
  wire [15:0] #10 Id_IM = IfId_IR[15:0];
  wire [15:0] #10 Id_address = IfId_IR[25:0];

  wire [31:0] #10 Id_SignExtImm = {{16{Id_IM[15]}}, Id_IM[15:0]};
  wire [31:0] #10 Id_JumpAddr   = {IfId_PC[31:28], Id_address, 2'h0};
  wire [31:0] #10 Id_BranchAddr = {{14{Id_IM[15]}}, Id_IM[15:0], 2'h0};

  wire [4:0]  #20 Id_RDST = (Id_OP==6'h23 || Id_OP==6'h8) ? Id_RT : Id_RD;
  wire [31:0] #20 Id_TPC = (Id_OP==6'h2) ? Id_JumpAddr : IfId_NPC+Id_BranchAddr;

  wire [31:0] Id_RRS, Id_RRT;
  GPR regfile(CLK, Id_RS, Id_RT, MaWb_RDST, MaWb_RSLT, MaWb_We, Id_RRS, Id_RRT);

  reg [31:0] IdEx_RRS, IdEx_rrt, IdEx_RRT, IdEx_TPC;
  reg [4:0]  IdEx_RDST;
  reg [5:0]  IdEx_OP;
  always @(posedge CLK) begin
    IdEx_OP   <= #5 (!RST_X) ? 0 : Id_OP;
    IdEx_RRS  <= #5 (!RST_X) ? 0 : Id_RRS;
    IdEx_rrt  <= #5 (!RST_X) ? 0 : Id_RRT;
    IdEx_RRT  <= #5 (!RST_X) ? 0 : (Id_OP==6'h8 || Id_OP==6'h23 || Id_OP==6'h2b)
                                   ? Id_SignExtImm : Id_RRT;
    IdEx_RDST <= #5 (!RST_X) ? 0 : Id_RDST;
    IdEx_TPC  <= #5 (!RST_X) ? 0 : Id_TPC;
  end
  /***************************************** EX Stage  **********************/
  wire [31:0] #20 Ex_RSLT = IdEx_RRS + IdEx_RRT;
  wire        #20 Ex_TKN  = ((IdEx_OP==6'h4 && (IdEx_RRS==IdEx_RRT)) ||
                             (IdEx_OP==6'h5 && (IdEx_RRS!=IdEx_RRT)) ||
                             (IdEx_OP==6'h2));

  reg [31:0] ExMa_rrt, ExMa_RSLT;
  reg [5:0]  ExMa_OP;
  reg [4:0]  ExMa_RDST;
  always @(posedge CLK) ExMa_rrt <= #5 (!RST_X) ? 0 : IdEx_rrt;
  always @(posedge CLK) ExMa_RSLT <= #5 (!RST_X) ? 0 : Ex_RSLT;
  always @(posedge CLK) ExMa_OP   <= #5 (!RST_X) ? 0 : IdEx_OP;
  always @(posedge CLK) ExMa_RDST <= #5 (!RST_X) ? 0 : IdEx_RDST;
  /***************************************** MA Stage  **********************/
  wire [31:0] Ma_dmout;
  MEM dm(CLK, ExMa_RSLT, ExMa_rrt, ExMa_OP==6'h2b ? 1'd1: 1'd0, Ma_dmout);

  wire WE = (ExMa_OP == 0 || ExMa_OP == 6'h8 || ExMa_OP == 6'h23) ? 1 : 0;

  reg [31:0] MaWb_RSLT;
  reg        MaWb_We;
  reg [4:0]  MaWb_RDST;
  always @(posedge CLK) MaWb_RSLT <= #5 (!RST_X) ? 0 :
                                      ((ExMa_OP==6'h23) ? Ma_dmout : ExMa_RSLT);
  always @(posedge CLK) MaWb_We   <= #5 (RST_X && WE) ? 1 : 0;
  always @(posedge CLK) MaWb_RDST <= #5 (!RST_X) ? 0 : ExMa_RDST;
  /***************************************** WB Stage  **********************/
endmodule

/******************************************************************************/
module MEM(CLK, ADDR, D_IN, D_WE, D_OUT); /* Instruction & Data Memory */
  input  wire        CLK;
  input  wire [31:0] ADDR, D_IN;
  input  wire        D_WE;
  output wire [31:0] D_OUT;

  reg [31:0] mem[0:1024*8-1]; /* 8K word memory */
  assign #15 D_OUT = mem[ADDR[14:2]];
  always @(posedge CLK) if(D_WE) mem[ADDR[14:2]] <= #10 D_IN;
endmodule

/* 32bitx32 2R/1W General Purpose Registers (Register File)                   */
/******************************************************************************/
module GPR(CLK, REGNUM0, REGNUM1, REGNUM2, DIN0, WE0, DOUT0, DOUT1);
  input  wire        CLK;
  input  wire  [4:0] REGNUM0, REGNUM1, REGNUM2;
  input  wire [31:0] DIN0;
  input  wire        WE0;
  output wire [31:0] DOUT0, DOUT1;

  reg [31:0] r[0:31];
  assign #15 DOUT0 = (REGNUM0==0) ? 0 : r[REGNUM0];
  assign #15 DOUT1 = (REGNUM1==0) ? 0 : r[REGNUM1];
  always @(negedge CLK) if(WE0) r[REGNUM2] <= #10 DIN0;
//  always @(posedge CLK) if(WE0) r[REGNUM2] <= #10 DIN0;
endmodule
/******************************************************************************/

titech/CSC.T433.AdvancedComputerArchitecture/final/code1-1.vcd
$date
	Mon Feb 14 21:35:12 2022
$end
$version
	Icarus Verilog
$end
$timescale
	100ps
$end
$scope module top $end
$scope module p $end
$var wire 1 ! CLK $end
$var wire 1 " Ex_TKN $end
$var wire 1 # RST_X $end
$var wire 1 $ WE $end
$var wire 32 % Ma_dmout [31:0] $end
$var wire 32 & If_NPC [31:0] $end
$var wire 32 ' If_IR [31:0] $end
$var wire 16 ( Id_address [15:0] $end
$var wire 32 ) Id_TPC [31:0] $end
$var wire 32 * Id_SignExtImm [31:0] $end
$var wire 5 + Id_RT [4:0] $end
$var wire 5 , Id_RS [4:0] $end
$var wire 32 - Id_RRT [31:0] $end
$var wire 32 . Id_RRS [31:0] $end
$var wire 5 / Id_RDST [4:0] $end
$var wire 5 0 Id_RD [4:0] $end
$var wire 6 1 Id_OP [5:0] $end
$var wire 32 2 Id_JumpAddr [31:0] $end
$var wire 16 3 Id_IM [15:0] $end
$var wire 32 4 Id_BranchAddr [31:0] $end
$var wire 32 5 Ex_RSLT [31:0] $end
$var reg 6 6 ExMa_OP [5:0] $end
$var reg 5 7 ExMa_RDST [4:0] $end
$var reg 32 8 ExMa_RSLT [31:0] $end
$var reg 32 9 ExMa_rrt [31:0] $end
$var reg 6 : IdEx_OP [5:0] $end
$var reg 5 ; IdEx_RDST [4:0] $end
$var reg 32 < IdEx_RRS [31:0] $end
$var reg 32 = IdEx_RRT [31:0] $end
$var reg 32 > IdEx_TPC [31:0] $end
$var reg 32 ? IdEx_rrt [31:0] $end
$var reg 32 @ IfId_IR [31:0] $end
$var reg 32 A IfId_NPC [31:0] $end
$var reg 32 B IfId_PC [31:0] $end
$var reg 5 C MaWb_RDST [4:0] $end
$var reg 32 D MaWb_RSLT [31:0] $end
$var reg 1 E MaWb_We $end
$var reg 32 F PC [31:0] $end
$scope module dm $end
$var wire 32 G ADDR [31:0] $end
$var wire 1 ! CLK $end
$var wire 32 H D_IN [31:0] $end
$var wire 32 I D_OUT [31:0] $end
$var wire 1 J D_WE $end
$upscope $end
$scope module imem $end
$var wire 32 K ADDR [31:0] $end
$var wire 1 ! CLK $end
$var wire 32 L D_IN [31:0] $end
$var wire 32 M D_OUT [31:0] $end
$var wire 1 N D_WE $end
$upscope $end
$scope module regfile $end
$var wire 1 ! CLK $end
$var wire 32 O DIN0 [31:0] $end
$var wire 5 P REGNUM0 [4:0] $end
$var wire 5 Q REGNUM1 [4:0] $end
$var wire 5 R REGNUM2 [4:0] $end
$var wire 1 E WE0 $end
$var wire 32 S DOUT1 [31:0] $end
$var wire 32 T DOUT0 [31:0] $end
$upscope $end
$upscope $end
$upscope $end
$enddefinitions $end
#0
$dumpvars
bx T
bx S
bx R
bx Q
bx P
bx O
0N
bx M
b0 L
bx K
xJ
bx I
bx H
bx G
bx F
xE
bx D
bx C
bx B
bx A
bx @
bx ?
bx >
bx =
bx <
bx ;
bx :
bx 9
bx 8
bx 7
bx 6
bx 5
bx 4
bx 3
bx 2
bx 1
bx 0
bx /
bx .
bx -
bx ,
bx +
bx *
bx )
bx (
bx '
bx &
bx %
x$
0#
x"
1!
$end
#50
1$
0J
b0 F
b0 K
b0 @
b0 B
b0 A
b0 >
b0 ;
b0 =
b0 ?
b0 <
b0 :
b0 9
b0 H
b0 8
b0 G
b0 6
b0 7
b0 D
b0 O
0E
b0 C
b0 R
#100
bx00 4
#150
b0 (
b0 1
b0 ,
b0 P
b0 +
b0 Q
b0 0
b0 3
b0xxxxxxxxxxxxxxxx00 2
#200
b1000000000100000 '
b1000000000100000 M
#250
b0 2
b0 *
b0 4
0"
b100 &
b0 5
#300
b0 .
b0 T
b0 -
b0 S
#350
b0 /
#450
b0 )
#500
0!
#1000
1!
#1400
1#
#1500
0!
#2000
1!
#2050
b100 F
b100 K
b1000000000100000 @
b100 A
1E
#2150
b1000000000100000 (
b10000 0
b1000000000100000 3
#2200
b100000000010000000000000000010 '
b100000000010000000000000000010 M
#2250
b100000000010000000 2
b11111111111111111000000000100000 *
b11111111111111100000000010000000 4
b100 )
b1000 &
#2350
b10000 /
#2450
b11111111111111100000000010000100 )
#2500
0!
#3000
1!
#3050
b11111111111111100000000010000100 >
b10000 ;
b1000 A
b100 B
b100000000010000000000000000010 @
b1000 F
b1000 K
#3150
b10 (
b1000 1
b1000 +
b1000 Q
b0 0
b10 3
#3200
b100100000100000 '
b100100000100000 M
#3250
b1000 2
b10 *
b1000 4
b11111111111111100000000010001000 )
b1100 &
#3300
bx -
bx S
#3350
b1000 /
#3450
b10000 )
#3500
0!
#4000
1!
#4050
b1100 F
b1100 K
b100100000100000 @
b1000 B
b1100 A
b10000 >
b1000 ;
b10 =
bx ?
b1000 :
b10000 7
#4150
b100100000100000 (
b0 1
b0 +
b0 Q
b1001 0
b100100000100000 3
#4200
b100000 '
b100000 M
#4250
b10010000010000000 2
b100100000100000 *
b10010000010000000 4
b10100 )
b10000 &
b10 5
#4300
b0 -
b0 S
#4350
b1001 /
#4450
b10010000010001100 )
#4500
0!
#5000
1!
#5050
b10000 C
b10000 R
b1000 7
b1000 6
b10 8
b10 G
bx 9
bx H
b10010000010001100 >
b1001 ;
b0 =
b0 ?
b0 :
b10000 A
b1100 B
b100000 @
b10000 F
b10000 K
#5150
b100000 (
b0 0
b100000 3
#5250
b10000000 2
b100000 *
b10000000 4
b10010000010010000 )
b0 5
b10100 &
#5350
b0 /
#5450
b10010000 )
#5500
0!
#6000
1!
#6050
b10100 F
b10100 K
b10000 B
b10100 A
b10010000 >
b0 ;
b0 9
b0 H
b0 8
b0 G
b0 6
b1001 7
b10 D
b10 O
b1000 C
b1000 R
#6250
b10010100 )
b11000 &
#6500
0!
#7000
1!
#7050
b1001 C
b1001 R
b0 D
b0 O
b0 7
b10010100 >
b11000 A
b10100 B
b11000 F
b11000 K
#7200
b10001000010010000000000010110 '
b10001000010010000000000010110 M
#7250
b10011000 )
b11100 &
#7500
0!
#8000
1!
#8050
b11100 F
b11100 K
b10001000010010000000000010110 @
b11000 B
b11100 A
b10011000 >
b0 C
b0 R
#8150
b10110 (
b100 1
b1000 ,
b1000 P
b1001 +
b1001 Q
b10110 3
#8200
b100000 '
b100000 M
#8250
b1011000 2
b10110 *
b1011000 4
b10011100 )
b100000 &
#8300
b10 .
b10 T
#8450
b1110100 )
#8500
0!
#9000
1!
#9050
b1110100 >
b10 <
b100 :
b100000 A
b11100 B
b100000 @
b100000 F
b100000 K
#9150
b100000 (
b0 1
b0 ,
b0 P
b0 +
b0 Q
b100000 3
#9250
b10000000 2
b100000 *
b10000000 4
b1111000 )
b10 5
b100100 &
#9300
b0 .
b0 T
#9450
b10100000 )
#9500
0!
#10000
1!
#10050
0$
b100100 F
b100100 K
b100000 B
b100100 A
b10100000 >
b0 <
b0 :
b10 8
b10 G
b100 6
#10200
b101000000100000 '
b101000000100000 M
#10250
b10100100 )
b101000 &
b0 5
#10500
0!
#11000
1!
#11050
1$
0E
b10 D
b10 O
b0 6
b0 8
b0 G
b10100100 >
b101000 A
b100100 B
b101000000100000 @
b101000 F
b101000 K
#11150
b101000000100000 (
b1010 0
b101000000100000 3
#11200
b100000 '
b100000 M
#11250
b10100000010000000 2
b101000000100000 *
b10100000010000000 4
b10101000 )
b101100 &
#11350
b1010 /
#11450
b10100000010101000 )
#11500
0!
#12000
1!
#12050
b101100 F
b101100 K
b100000 @
b101000 B
b101100 A
b10100000010101000 >
b1010 ;
b0 D
b0 O
1E
#12150
b100000 (
b0 0
b100000 3
#12250
b10000000 2
b100000 *
b10000000 4
b10100000010101100 )
b110000 &
#12350
b0 /
#12450
b10101100 )
#12500
0!
#13000
1!
#13050
b1010 7
b10101100 >
b0 ;
b110000 A
b101100 B
b110000 F
b110000 K
#13250
b10110000 )
b110100 &
#13500
0!
#14000
1!
#14050
b110100 F
b110100 K
b110000 B
b110100 A
b10110000 >
b0 7
b1010 C
b1010 R
#14200
b10001000010100000000000001011 '
b10001000010100000000000001011 M
#14250
b10110100 )
b111000 &
#14500
0!
#15000
1!
#15050
b0 C
b0 R
b10110100 >
b111000 A
b110100 B
b10001000010100000000000001011 @
b111000 F
b111000 K
#15150
b1011 (
b100 1
b1000 ,
b1000 P
b1010 +
b1010 Q
b1011 3
#15200
b100000 '
b100000 M
#15250
b101100 2
b1011 *
b101100 4
b10111000 )
b111100 &
#15300
b10 .
b10 T
#15450
b1100100 )
#15500
0!
#16000
1!
#16050
b111100 F
b111100 K
b100000 @
b111000 B
b111100 A
b1100100 >
b10 <
b100 :
#16150
b100000 (
b0 1
b0 ,
b0 P
b0 +
b0 Q
b100000 3
#16250
b10000000 2
b100000 *
b10000000 4
b1101000 )
b1000000 &
b10 5
#16300
b0 .
b0 T
#16450
b10111100 )
#16500
0!
#17000
1!
#17050
0$
b100 6
b10 8
b10 G
b10111100 >
b0 <
b0 :
b1000000 A
b111100 B
b1000000 F
b1000000 K
#17200
b1001010100101100000100000 '
b1001010100101100000100000 M
#17250
b11000000 )
b0 5
b1000100 &
#17500
0!
#18000
1!
#18050
1$
b1000100 F
b1000100 K
b1001010100101100000100000 @
b1000000 B
b1000100 A
b11000000 >
b0 8
b0 G
b0 6
b10 D
b10 O
0E
#18150
b101100000100000 (
b1001 ,
b1001 P
b1010 +
b1010 Q
b1011 0
b101100000100000 3
#18200
b100000 '
b100000 M
#18250
b10110000010000000 2
b101100000100000 *
b10110000010000000 4
b11000100 )
b1001000 &
#18350
b1011 /
#18450
b10110000011000100 )
#18500
0!
#19000
1!
#19050
1E
b0 D
b0 O
b10110000011000100 >
b1011 ;
b1001000 A
b1000100 B
b100000 @
b1001000 F
b1001000 K
#19150
b100000 (
b0 ,
b0 P
b0 +
b0 Q
b0 0
b100000 3
#19250
b10000000 2
b100000 *
b10000000 4
b10110000011001000 )
b1001100 &
#19350
b0 /
#19450
b11001000 )
#19500
0!
#20000
1!
#20050
b1001100 F
b1001100 K
b1001000 B
b1001100 A
b11001000 >
b0 ;
b1011 7
#20250
b11001100 )
b1010000 &
#20500
0!
#21000
1!
#21050
b1011 C
b1011 R
b0 7
b11001100 >
b1010000 A
b1001100 B
b1010000 F
b1010000 K
#21200
b10000010111000000000100000 '
b10000010111000000000100000 M
#21250
b11010000 )
b1010100 &
#21500
0!
#22000
1!
#22050
b1010100 F
b1010100 K
b10000010111000000000100000 @
b1010000 B
b1010100 A
b11010000 >
b0 C
b0 R
#22150
b1000000000100000 (
b10000 ,
b10000 P
b1011 +
b1011 Q
b10000 0
b1000000000100000 3
#22200
b100001010010100000000000000001 '
b100001010010100000000000000001 M
#22250
b100000000010000000 2
b11111111111111111000000000100000 *
b11111111111111100000000010000000 4
b11010100 )
b1011000 &
#22350
b10000 /
#22450
b11111111111111100000000011010100 )
#22500
0!
#23000
1!
#23050
b11111111111111100000000011010100 >
b10000 ;
b1011000 A
b1010100 B
b100001010010100000000000000001 @
b1011000 F
b1011000 K
#23150
b1 (
b1000 1
b1010 ,
b1010 P
b1010 +
b1010 Q
b0 0
b1 3
#23200
b1000000000000000000000001101 '
b1000000000000000000000001101 M
#23250
b100 2
b1 *
b100 4
b11111111111111100000000011011000 )
b1011100 &
#23350
b1010 /
#23450
b1011100 )
#23500
0!
#24000
1!
#24050
b1011100 F
b1011100 K
b1000000000000000000000001101 @
b1011000 B
b1011100 A
b1011100 >
b1010 ;
b1 =
b1000 :
b10000 7
#24150
b1101 (
b10 1
b0 ,
b0 P
b0 +
b0 Q
b1101 3
#24200
b100000 '
b100000 M
#24250
b110100 2
b1101 *
b110100 4
b1100000 &
b1 5
#24350
b0 /
#24450
b110100 )
#24500
0!
#25000
1!
#25050
b10000 C
b10000 R
b1010 7
b1000 6
b1 8
b1 G
b110100 >
b0 ;
b0 =
b10 :
b1100000 A
b1011100 B
b100000 @
b1100000 F
b1100000 K
#25150
b100000 (
b0 1
b100000 3
#25250
b10000000 2
b100000 *
b10000000 4
1"
b0 5
b1100100 &
#25450
b11100000 )
#25500
0!
#26000
1!
#26050
0$
b110100 F
b110100 K
b1100000 B
b1100100 A
b11100000 >
b0 :
b0 8
b0 G
b10 6
b0 7
b1 D
b1 O
b1010 C
b1010 R
#26200
b10001000010100000000000001011 '
b10001000010100000000000001011 M
#26250
b11100100 )
0"
b111000 &
#26500
0!
#27000
1!
#27050
1$
b0 C
b0 R
0E
b0 D
b0 O
b0 6
b11100100 >
b111000 A
b110100 B
b10001000010100000000000001011 @
b111000 F
b111000 K
#27150
b1011 (
b100 1
b1000 ,
b1000 P
b1010 +
b1010 Q
b1011 3
#27200
b100000 '
b100000 M
#27250
b101100 2
b1011 *
b101100 4
b10111000 )
b111100 &
#27300
b10 .
b10 T
b1 -
b1 S
#27450
b1100100 )
#27500
0!
#28000
1!
#28050
b111100 F
b111100 K
b100000 @
b111000 B
b111100 A
b1100100 >
b1 =
b1 ?
b10 <
b100 :
1E
#28150
b100000 (
b0 1
b0 ,
b0 P
b0 +
b0 Q
b100000 3
#28250
b10000000 2
b100000 *
b10000000 4
b1101000 )
b1000000 &
b11 5
#28300
b0 .
b0 T
b0 -
b0 S
#28450
b10111100 )
#28500
0!
#29000
1!
#29050
0$
b100 6
b11 8
b11 G
b1 9
b1 H
b10111100 >
b0 =
b0 ?
b0 <
b0 :
b1000000 A
b111100 B
b1000000 F
b1000000 K
#29200
b1001010100101100000100000 '
b1001010100101100000100000 M
#29250
b11000000 )
b0 5
b1000100 &
#29500
0!
#30000
1!
#30050
1$
b1000100 F
b1000100 K
b1001010100101100000100000 @
b1000000 B
b1000100 A
b11000000 >
b0 9
b0 H
b0 8
b0 G
b0 6
b11 D
b11 O
0E
#30150
b101100000100000 (
b1001 ,
b1001 P
b1010 +
b1010 Q
b1011 0
b101100000100000 3
#30200
b100000 '
b100000 M
#30250
b10110000010000000 2
b101100000100000 *
b10110000010000000 4
b11000100 )
b1001000 &
#30300
b1 -
b1 S
#30350
b1011 /
#30450
b10110000011000100 )
#30500
0!
#31000
1!
#31050
1E
b0 D
b0 O
b10110000011000100 >
b1011 ;
b1 =
b1 ?
b1001000 A
b1000100 B
b100000 @
b1001000 F
b1001000 K
#31150
b100000 (
b0 ,
b0 P
b0 +
b0 Q
b0 0
b100000 3
#31250
b10000000 2
b100000 *
b10000000 4
b10110000011001000 )
b1 5
b1001100 &
#31300
b0 -
b0 S
#31350
b0 /
#31450
b11001000 )
#31500
0!
#32000
1!
#32050
b1001100 F
b1001100 K
b1001000 B
b1001100 A
b11001000 >
b0 ;
b0 =
b0 ?
b1 9
b1 H
b1 8
b1 G
b1011 7
#32250
b11001100 )
b1010000 &
b0 5
#32500
0!
#33000
1!
#33050
b1011 C
b1011 R
b1 D
b1 O
b0 7
b0 8
b0 G
b0 9
b0 H
b11001100 >
b1010000 A
b1001100 B
b1010000 F
b1010000 K
#33200
b10000010111000000000100000 '
b10000010111000000000100000 M
#33250
b11010000 )
b1010100 &
#33500
0!
#34000
1!
#34050
b1010100 F
b1010100 K
b10000010111000000000100000 @
b1010000 B
b1010100 A
b11010000 >
b0 D
b0 O
b0 C
b0 R
#34150
b1000000000100000 (
b10000 ,
b10000 P
b1011 +
b1011 Q
b10000 0
b1000000000100000 3
#34200
b100001010010100000000000000001 '
b100001010010100000000000000001 M
#34250
b100000000010000000 2
b11111111111111111000000000100000 *
b11111111111111100000000010000000 4
b11010100 )
b1011000 &
#34300
b1 -
b1 S
#34350
b10000 /
#34450
b11111111111111100000000011010100 )
#34500
0!
#35000
1!
#35050
b11111111111111100000000011010100 >
b10000 ;
b1 =
b1 ?
b1011000 A
b1010100 B
b100001010010100000000000000001 @
b1011000 F
b1011000 K
#35150
b1 (
b1000 1
b1010 ,
b1010 P
b1010 +
b1010 Q
b0 0
b1 3
#35200
b1000000000000000000000001101 '
b1000000000000000000000001101 M
#35250
b100 2
b1 *
b100 4
b11111111111111100000000011011000 )
b1 5
b1011100 &
#35300
b1 .
b1 T
#35350
b1010 /
#35450
b1011100 )
#35500
0!
#36000
1!
#36050
b1011100 F
b1011100 K
b1000000000000000000000001101 @
b1011000 B
b1011100 A
b1011100 >
b1010 ;
b1 <
b1000 :
b1 9
b1 H
b1 8
b1 G
b10000 7
#36150
b1101 (
b10 1
b0 ,
b0 P
b0 +
b0 Q
b1101 3
#36200
b100000 '
b100000 M
#36250
b110100 2
b1101 *
b110100 4
b1100000 &
b10 5
#36300
b0 .
b0 T
b0 -
b0 S
#36350
b0 /
#36450
b110100 )
#36500
0!
#37000
1!
#37050
b10000 C
b10000 R
b1 D
b1 O
b1010 7
b1000 6
b10 8
b10 G
b110100 >
b0 ;
b0 =
b0 ?
b0 <
b10 :
b1100000 A
b1011100 B
b100000 @
b1100000 F
b1100000 K
#37150
b100000 (
b0 1
b100000 3
#37250
b10000000 2
b100000 *
b10000000 4
1"
b0 5
b1100100 &
#37450
b11100000 )
#37500
0!
#38000
1!
#38050
0$
b110100 F
b110100 K
b1100000 B
b1100100 A
b11100000 >
b0 :
b0 9
b0 H
b0 8
b0 G
b10 6
b0 7
b10 D
b10 O
b1010 C
b1010 R
#38200
b10001000010100000000000001011 '
b10001000010100000000000001011 M
#38250
b11100100 )
0"
b111000 &
#38500
0!
#39000
1!
#39050
1$
b0 C
b0 R
0E
b0 D
b0 O
b0 6
b11100100 >
b111000 A
b110100 B
b10001000010100000000000001011 @
b111000 F
b111000 K
#39150
b1011 (
b100 1
b1000 ,
b1000 P
b1010 +
b1010 Q
b1011 3
#39200
b100000 '
b100000 M
#39250
b101100 2
b1011 *
b101100 4
b10111000 )
b111100 &
#39300
b10 .
b10 T
b10 -
b10 S
#39450
b1100100 )
#39500
0!
#40000
1!
#40050
b111100 F
b111100 K
b100000 @
b111000 B
b111100 A
b1100100 >
b10 =
b10 ?
b10 <
b100 :
1E
#40150
b100000 (
b0 1
b0 ,
b0 P
b0 +
b0 Q
b100000 3
#40250
b10000000 2
b100000 *
b10000000 4
1"
b1101000 )
b1000000 &
b100 5
#40300
b0 .
b0 T
b0 -
b0 S
#40450
b10111100 )
#40500
0!
#41000
1!
#41050
0$
b100 6
b100 8
b100 G
b10 9
b10 H
b10111100 >
b0 =
b0 ?
b0 <
b0 :
b1000000 A
b111100 B
b1100100 F
b1100100 K
#41200
b100001001010010000000000000001 '
b100001001010010000000000000001 M
#41250
0"
b11000000 )
b0 5
b1101000 &
#41500
0!
#42000
1!
