titech/CSC.T433.AdvancedComputerArchitecture/bne/bne.v
/******************************************************************************/
/* Simple Processor Ver.07                    2018-12-18  ArchLab. TOKYO TECH */
/* Four stage pipelined processor supporting ADD and BNE,                     */
/* which has no data forwarding                                               */
/******************************************************************************/
`default_nettype none
`timescale 1ns/100ps
/******************************************************************************/
module top();
  reg CLK, RST_X;
  initial begin CLK = 1; forever #50 CLK = ~CLK; end
  initial begin RST_X = 0; #140 RST_X = 1;       end
  initial begin $dumpfile("wave.vcd"); $dumpvars(0, p); end

  initial begin /* initialize the instruction & data memory  & regfile */
    p.imem.mem[0] = {6'h0, 5'd0, 5'd0, 5'd0, 5'd0, 6'h20};  //   NOP
    p.imem.mem[1] = {6'h0, 5'd5, 5'd1, 5'd5, 5'd0, 6'h20};  // L1:
                                                            //   add  $5, $5, $1
    p.imem.mem[2] = {6'h0, 5'd0, 5'd0, 5'd0, 5'd0, 6'h20};  //   NOP
    p.imem.mem[3] = {6'h0, 5'd0, 5'd0, 5'd0, 5'd0, 6'h20};  //   NOP
    p.imem.mem[4] = {6'h0, 5'd0, 5'd0, 5'd0, 5'd0, 6'h20};  //   NOP
    p.imem.mem[5] = {6'h5, 5'd4, 5'd5, 16'hfffb};           //   bne  $4, $5, L1
    p.imem.mem[6] = {6'h0, 5'd0, 5'd0, 5'd0, 5'd0, 6'h20};  //   NOP
    p.imem.mem[7] = {6'h0, 5'd0, 5'd0, 5'd0, 5'd0, 6'h20};  //   NOP
    p.imem.mem[8] = {6'h0, 5'd0, 5'd0, 5'd5, 5'd0, 6'h20};  //   add  $5, $0, $0
    p.imem.mem[9] = {6'h0, 5'd0, 5'd0, 5'd0, 5'd0, 6'h20};  //   NOP
    p.imem.mem[10]= {6'h0, 5'd0, 5'd0, 5'd0, 5'd0, 6'h20};  //   NOP
    p.imem.mem[11]= {6'h5, 5'd2, 5'd0, 16'hfff5};           //   bne  $2, $0, L1
    p.imem.mem[12]= {6'h0, 5'd0, 5'd0, 5'd0, 5'd0, 6'h20};  //   NOP
    p.imem.mem[13]= {6'h0, 5'd0, 5'd0, 5'd0, 5'd0, 6'h20};  //   NOP

    p.regfile.r[1] = 1;
    p.regfile.r[2] = 22;
    p.regfile.r[3] = 0;
    p.regfile.r[4] = 4;
    p.regfile.r[5] = 0;
  end
  initial #30000 $finish();

  always @(posedge CLK) begin
    if(p.IdEx_OP==6'h5) $write("RRS, RRT, TKN:%8d %8d  %8d\n",
                               p.IdEx_RRS,p.IdEx_RRT,p.Ex_TKN);
  end

  PROCESSOR_07 p(CLK, RST_X);
endmodule

/******************************************************************************/
module PROCESSOR_07(CLK, RST_X);
  input wire CLK, RST_X;

  /***************************************** IF Stage  **********************/
  reg  [31:0] PC;
  wire [31:0] NextPC = Ex_TKN ? IdEx_TPC : PC+4;
  always @(posedge CLK) PC <= #5 (!RST_X) ? 0 : NextPC;

  wire [31:0] If_IR;
  MEM imem(CLK, PC, 32'd0, 1'd0, If_IR);

  reg [31:0] IfId_IR, IfId_NPC;
  always @(posedge CLK) IfId_IR  <= #5 (!RST_X) ? 0 : If_IR;
  always @(posedge CLK) IfId_NPC <= #5 (!RST_X) ? 0 : PC+4;
  /***************************************** ID Stage  **********************/
  wire [5:0]  #10 Id_OP  = IfId_IR[31:26];
  wire [4:0]  #10 Id_RS  = IfId_IR[25:21];
  wire [4:0]  #10 Id_RT  = IfId_IR[20:16];
  wire [4:0]  #10 Id_RD  = IfId_IR[15:11];
  wire [15:0] #10 Id_IMM = IfId_IR[15:0];
  wire [31:0]     Id_BranchAddr = Id_OP == 6'h5 ?
                                  {{16{Id_IMM[15]}}, Id_IMM[15:0]} << 2 : 0;

  wire [31:0] Id_RRS, Id_RRT;
  GPR regfile(CLK, Id_RS, Id_RT, ExWb_RD, ExWb_RSLT, ExWb_OP == 6'h0 ? 1 : 0,
              Id_RRS, Id_RRT);

  reg [5:0]  IdEx_OP;
  reg [31:0] IdEx_RRS, IdEx_RRT, IdEx_TPC;
  reg [4:0]  IdEx_RD;
  always @(posedge CLK) IdEx_OP  <= #5 (!RST_X) ? 0 : Id_OP;
  always @(posedge CLK) IdEx_RRS <= #5 (!RST_X) ? 0 : Id_RRS;
  always @(posedge CLK) IdEx_RRT <= #5 (!RST_X) ? 0 : Id_RRT;
  always @(posedge CLK) IdEx_RD  <= #5 (!RST_X) ? 0 : Id_RD;
  always @(posedge CLK) IdEx_TPC <= #5 (!RST_X) ? 0 : IfId_NPC + Id_BranchAddr;
  /***************************************** EX Stage  **********************/
  wire [31:0] #20 Ex_RSLT = IdEx_RRS + IdEx_RRT;
  wire        #20 Ex_TKN  = (IdEx_OP == 6'h5) ? IdEx_RRS != IdEx_RRT : 0;

  reg [5:0]  ExWb_OP;
  reg [31:0] ExWb_RSLT;
  reg [4:0]  ExWb_RD;
  always @(posedge CLK) ExWb_OP   <= #5 (!RST_X) ? 0 : IdEx_OP;
  // It's unnecessary to assign ExWb_RSLT and ExWb_RD by IdEx_OP because WE0
  // will be set by ExWb_OP properly, but I still do this for a clear wave.
  always @(posedge CLK) ExWb_RSLT <= #5 (!RST_X) ? 0 :
                                           (IdEx_OP == 6'h5) ? 0 : Ex_RSLT;
  always @(posedge CLK) ExWb_RD   <= #5 (!RST_X) ? 0 :
                                           (IdEx_OP == 6'h5) ? 0 : IdEx_RD;
  /***************************************** WB Stage  **********************/

endmodule

/******************************************************************************/
module MEM(CLK, ADDR, D_IN, D_WE, D_OUT); /* Instruction & Data Memory */
  input  wire        CLK;
  input  wire [31:0] ADDR, D_IN;
  input  wire        D_WE;
  output wire [31:0] D_OUT;

  reg [31:0] mem[0:1024*8-1]; /* 8K word memory */
  assign #15 D_OUT = mem[ADDR[14:2]];
  always @(posedge CLK) if(D_WE) mem[ADDR[14:2]] <= #10 D_IN;
endmodule

/* 32bitx32 2R/1W General Purpose Registers (Register File)                   */
/******************************************************************************/
module GPR(CLK, REGNUM0, REGNUM1, REGNUM2, DIN0, WE0, DOUT0, DOUT1);
  input  wire        CLK;
  input  wire  [4:0] REGNUM0, REGNUM1, REGNUM2;
  input  wire [31:0] DIN0;
  input  wire        WE0;
  output wire [31:0] DOUT0, DOUT1;

  reg [31:0] r[0:31];
  assign #15 DOUT0 = (REGNUM0==0) ? 0 : r[REGNUM0];
  assign #15 DOUT1 = (REGNUM1==0) ? 0 : r[REGNUM1];
  always @(negedge CLK) if(WE0) r[REGNUM2] <= #10 DIN0;
//  always @(posedge CLK) if(WE0) r[REGNUM2] <= #10 DIN0;
endmodule
/******************************************************************************/

titech/CSC.T433.AdvancedComputerArchitecture/bne/wave.vcd
$date
	Sun Jan  9 14:00:47 2022
$end
$version
	Icarus Verilog
$end
$timescale
	100ps
$end
$scope module top $end
$scope module p $end
$var wire 1 ! CLK $end
$var wire 1 " RST_X $end
$var wire 32 # NextPC [31:0] $end
$var wire 32 $ If_IR [31:0] $end
$var wire 5 % Id_RT [4:0] $end
$var wire 5 & Id_RS [4:0] $end
$var wire 32 ' Id_RRT [31:0] $end
$var wire 32 ( Id_RRS [31:0] $end
$var wire 5 ) Id_RD [4:0] $end
$var wire 6 * Id_OP [5:0] $end
$var wire 16 + Id_IMM [15:0] $end
$var wire 32 , Id_BranchAddr [31:0] $end
$var wire 1 - Ex_TKN $end
$var wire 32 . Ex_RSLT [31:0] $end
$var reg 6 / ExWb_OP [5:0] $end
$var reg 5 0 ExWb_RD [4:0] $end
$var reg 32 1 ExWb_RSLT [31:0] $end
$var reg 6 2 IdEx_OP [5:0] $end
$var reg 5 3 IdEx_RD [4:0] $end
$var reg 32 4 IdEx_RRS [31:0] $end
$var reg 32 5 IdEx_RRT [31:0] $end
$var reg 32 6 IdEx_TPC [31:0] $end
$var reg 32 7 IfId_IR [31:0] $end
$var reg 32 8 IfId_NPC [31:0] $end
$var reg 32 9 PC [31:0] $end
$scope module imem $end
$var wire 32 : ADDR [31:0] $end
$var wire 1 ! CLK $end
$var wire 32 ; D_IN [31:0] $end
$var wire 32 < D_OUT [31:0] $end
$var wire 1 = D_WE $end
$upscope $end
$scope module regfile $end
$var wire 1 ! CLK $end
$var wire 32 > DIN0 [31:0] $end
$var wire 5 ? REGNUM0 [4:0] $end
$var wire 5 @ REGNUM1 [4:0] $end
$var wire 5 A REGNUM2 [4:0] $end
$var wire 1 B WE0 $end
$var wire 32 C DOUT1 [31:0] $end
$var wire 32 D DOUT0 [31:0] $end
$upscope $end
$upscope $end
$upscope $end
$enddefinitions $end
#0
$dumpvars
bx D
bx C
xB
bx A
bx @
bx ?
bx >
0=
bx <
b0 ;
bx :
bx 9
bx 8
bx 7
bx 6
bx 5
bx 4
bx 3
bx 2
bx 1
bx 0
bx /
bx .
x-
bx00 ,
bx +
bx *
bx )
bx (
bx '
bx &
bx %
bx $
bx #
0"
1!
$end
#50
1B
b0x00 #
b0 9
b0 :
b0 7
b0 8
b0 2
b0 4
b0 5
b0 3
b0 6
b0 /
b0 1
b0 >
b0 0
b0 A
#150
b0 ,
b0 *
b0 &
b0 ?
b0 %
b0 @
b0 )
b0 +
#200
b100000 $
b100000 <
#250
b100 #
0-
b0 .
#300
b0 (
b0 D
b0 '
b0 C
#500
0!
#1000
1!
#1400
1"
#1500
0!
#2000
1!
#2050
b1000 #
b100 9
b100 :
b100000 7
b100 8
#2150
b100000 +
#2200
b101000010010100000100000 $
b101000010010100000100000 <
#2500
0!
#3000
1!
#3050
b1100 #
b100 6
b1000 8
b101000010010100000100000 7
b1000 9
b1000 :
#3150
b101 &
b101 ?
b1 %
b1 @
b101 )
b10100000100000 +
#3200
b100000 $
b100000 <
#3300
b1 '
b1 C
#3500
0!
#4000
1!
#4050
b10000 #
b1100 9
b1100 :
b100000 7
b1100 8
b1 5
b101 3
b1000 6
#4150
b0 &
b0 ?
b0 %
b0 @
b0 )
b100000 +
#4250
b1 .
#4300
b0 '
b0 C
#4500
0!
#5000
1!
#5050
b10100 #
b101 0
b101 A
b1 1
b1 >
b1100 6
b0 3
b0 5
b10000 8
b10000 9
b10000 :
#5250
b0 .
#5500
0!
#6000
1!
#6050
b11000 #
b10100 9
b10100 :
b10100 8
b10000 6
b0 1
b0 >
b0 0
b0 A
#6200
b10100100001011111111111111011 $
b10100100001011111111111111011 <
#6500
0!
#7000
1!
#7050
b11100 #
b10100 6
b11000 8
b10100100001011111111111111011 7
b11000 9
b11000 :
#7150
b11111111111111111111111111101100 ,
b101 *
b100 &
b100 ?
b101 %
b101 @
b11111 )
b1111111111111011 +
#7200
b100000 $
b100000 <
#7300
b100 (
b100 D
b1 '
b1 C
#7500
0!
#8000
1!
#8050
b100000 #
b11100 9
b11100 :
b100000 7
b11100 8
b101 2
b100 4
b1 5
b11111 3
b100 6
#8150
b0 ,
b0 *
b0 &
b0 ?
b0 %
b0 @
b0 )
b100000 +
#8250
b100 #
1-
b101 .
#8300
b0 (
b0 D
b0 '
b0 C
#8500
0!
#9000
1!
#9050
0B
b11100 #
b101 /
b11100 6
b0 3
b0 5
b0 4
b0 2
b100000 8
b100 9
b100 :
#9200
b101000010010100000100000 $
b101000010010100000100000 <
#9250
b1000 #
0-
b0 .
#9500
0!
#10000
1!
#10050
1B
b1100 #
b1000 9
b1000 :
b101000010010100000100000 7
b1000 8
b100000 6
b0 /
#10150
b101 &
b101 ?
b1 %
b1 @
b101 )
b10100000100000 +
#10200
b100000 $
b100000 <
#10300
b1 (
b1 D
b1 '
b1 C
#10500
0!
#11000
1!
#11050
b10000 #
b1000 6
b101 3
b1 5
b1 4
b1100 8
b100000 7
b1100 9
b1100 :
#11150
b0 &
b0 ?
b0 %
b0 @
b0 )
b100000 +
#11250
b10 .
#11300
b0 (
b0 D
b0 '
b0 C
#11500
0!
#12000
1!
#12050
b10100 #
b10000 9
b10000 :
b10000 8
b0 4
b0 5
b0 3
b1100 6
b10 1
b10 >
b101 0
b101 A
#12250
b0 .
#12500
0!
#13000
1!
#13050
b11000 #
b0 0
b0 A
b0 1
b0 >
b10000 6
b10100 8
b10100 9
b10100 :
#13200
b10100100001011111111111111011 $
b10100100001011111111111111011 <
#13500
0!
#14000
1!
#14050
b11100 #
b11000 9
b11000 :
b10100100001011111111111111011 7
b11000 8
b10100 6
#14150
b11111111111111111111111111101100 ,
b101 *
b100 &
b100 ?
b101 %
b101 @
b11111 )
b1111111111111011 +
#14200
b100000 $
b100000 <
#14300
b100 (
b100 D
b10 '
b10 C
#14500
0!
#15000
1!
#15050
b100000 #
b100 6
b11111 3
b10 5
b100 4
b101 2
b11100 8
b100000 7
b11100 9
b11100 :
#15150
b0 ,
b0 *
b0 &
b0 ?
b0 %
b0 @
b0 )
b100000 +
#15250
b100 #
1-
b110 .
#15300
b0 (
b0 D
b0 '
b0 C
#15500
0!
#16000
1!
#16050
0B
b11100 #
b100 9
b100 :
b100000 8
b0 2
b0 4
b0 5
b0 3
b11100 6
b101 /
#16200
b101000010010100000100000 $
b101000010010100000100000 <
#16250
b1000 #
0-
b0 .
#16500
0!
#17000
1!
#17050
1B
b1100 #
b0 /
b100000 6
b1000 8
b101000010010100000100000 7
b1000 9
b1000 :
#17150
b101 &
b101 ?
b1 %
b1 @
b101 )
b10100000100000 +
#17200
b100000 $
b100000 <
#17300
b10 (
b10 D
b1 '
b1 C
#17500
0!
#18000
1!
#18050
b10000 #
b1100 9
b1100 :
b100000 7
b1100 8
b10 4
b1 5
b101 3
b1000 6
#18150
b0 &
b0 ?
b0 %
b0 @
b0 )
b100000 +
#18250
b11 .
#18300
b0 (
b0 D
b0 '
b0 C
#18500
0!
#19000
1!
#19050
b10100 #
b101 0
b101 A
b11 1
b11 >
b1100 6
b0 3
b0 5
b0 4
b10000 8
b10000 9
b10000 :
#19250
b0 .
#19500
0!
#20000
1!
#20050
b11000 #
b10100 9
b10100 :
b10100 8
b10000 6
b0 1
b0 >
b0 0
b0 A
#20200
b10100100001011111111111111011 $
b10100100001011111111111111011 <
#20500
0!
#21000
1!
#21050
b11100 #
b10100 6
b11000 8
b10100100001011111111111111011 7
b11000 9
b11000 :
#21150
b11111111111111111111111111101100 ,
b101 *
b100 &
b100 ?
b101 %
b101 @
b11111 )
b1111111111111011 +
#21200
b100000 $
b100000 <
#21300
b100 (
b100 D
b11 '
b11 C
#21500
0!
#22000
1!
#22050
b100000 #
b11100 9
b11100 :
b100000 7
b11100 8
b101 2
b100 4
b11 5
b11111 3
b100 6
#22150
b0 ,
b0 *
b0 &
b0 ?
b0 %
b0 @
b0 )
b100000 +
#22250
b100 #
1-
b111 .
#22300
b0 (
b0 D
b0 '
b0 C
#22500
0!
#23000
1!
#23050
0B
b11100 #
b101 /
b11100 6
b0 3
b0 5
b0 4
b0 2
b100000 8
b100 9
b100 :
#23200
b101000010010100000100000 $
b101000010010100000100000 <
#23250
b1000 #
0-
b0 .
#23500
0!
#24000
1!
#24050
1B
b1100 #
b1000 9
b1000 :
b101000010010100000100000 7
b1000 8
b100000 6
b0 /
#24150
b101 &
b101 ?
b1 %
b1 @
b101 )
b10100000100000 +
#24200
b100000 $
b100000 <
#24300
b11 (
b11 D
b1 '
b1 C
#24500
0!
#25000
1!
#25050
b10000 #
b1000 6
b101 3
b1 5
b11 4
b1100 8
b100000 7
b1100 9
b1100 :
#25150
b0 &
b0 ?
b0 %
b0 @
b0 )
b100000 +
#25250
b100 .
#25300
b0 (
b0 D
b0 '
b0 C
#25500
0!
#26000
1!
#26050
b10100 #
b10000 9
b10000 :
b10000 8
b0 4
b0 5
b0 3
b1100 6
b100 1
b100 >
b101 0
b101 A
#26250
b0 .
#26500
0!
#27000
1!
#27050
b11000 #
b0 0
b0 A
b0 1
b0 >
b10000 6
b10100 8
b10100 9
b10100 :
#27200
b10100100001011111111111111011 $
b10100100001011111111111111011 <
#27500
0!
#28000
1!
#28050
b11100 #
b11000 9
b11000 :
b10100100001011111111111111011 7
b11000 8
b10100 6
#28150
b11111111111111111111111111101100 ,
b101 *
b100 &
b100 ?
b101 %
b101 @
b11111 )
b1111111111111011 +
#28200
b100000 $
b100000 <
#28300
b100 (
b100 D
b100 '
b100 C
#28500
0!
#29000
1!
#29050
b100000 #
b100 6
b11111 3
b100 5
b100 4
b101 2
b11100 8
b100000 7
b11100 9
b11100 :
#29150
b0 ,
b0 *
b0 &
b0 ?
b0 %
b0 @
b0 )
b100000 +
#29250
b1000 .
#29300
b0 (
b0 D
b0 '
b0 C
#29500
0!
#30000
1!
#30050
0B
b100100 #
b100000 9
b100000 :
b100000 8
b0 2
b0 4
b0 5
b0 3
b11100 6
b101 /
#30200
b10100000100000 $
b10100000100000 <
#30250
b0 .
#30500
0!
#31000
1!
#31050
1B
b101000 #
b0 /
b100000 6
b100100 8
b10100000100000 7
b100100 9
b100100 :
#31150
b101 )
b10100000100000 +
#31200
b100000 $
b100000 <
#31500
0!
#32000
1!
#32050
b101100 #
b101000 9
b101000 :
b100000 7
b101000 8
b101 3
b100100 6
#32150
b0 )
b100000 +
#32500
0!
#33000
1!
#33050
b110000 #
b101 0
b101 A
b101000 6
b0 3
b101100 8
b101100 9
b101100 :
#33200
b10100010000001111111111110101 $
b10100010000001111111111110101 <
#33500
0!
#34000
1!
#34050
b110100 #
b110000 9
b110000 :
b10100010000001111111111110101 7
b110000 8
b101100 6
b0 0
b0 A
#34150
b11111111111111111111111111010100 ,
b101 *
b10 &
b10 ?
b11111 )
b1111111111110101 +
#34200
b100000 $
b100000 <
#34300
b10110 (
b10110 D
#34500
0!
#35000
1!
#35050
b111000 #
b100 6
b11111 3
b10110 4
b101 2
b110100 8
b100000 7
b110100 9
b110100 :
#35150
b0 ,
b0 *
b0 &
b0 ?
b0 )
b100000 +
#35250
b100 #
1-
b10110 .
#35300
b0 (
b0 D
#35500
0!
#36000
1!
#36050
0B
b110100 #
b100 9
b100 :
b111000 8
b0 2
b0 4
b0 3
b110100 6
b101 /
#36200
b101000010010100000100000 $
b101000010010100000100000 <
#36250
b1000 #
0-
b0 .
#36500
0!
#37000
1!
#37050
1B
b1100 #
b0 /
b111000 6
b1000 8
b101000010010100000100000 7
b1000 9
b1000 :
#37150
b101 &
b101 ?
b1 %
b1 @
b101 )
b10100000100000 +
#37200
b100000 $
b100000 <
#37300
b1 '
b1 C
#37500
0!
#38000
1!
#38050
b10000 #
b1100 9
b1100 :
b100000 7
b1100 8
b1 5
b101 3
b1000 6
#38150
b0 &
b0 ?
b0 %
b0 @
b0 )
b100000 +
#38250
b1 .
#38300
b0 '
b0 C
#38500
0!
#39000
1!
#39050
b10100 #
b101 0
b101 A
b1 1
b1 >
b1100 6
b0 3
b0 5
b10000 8
b10000 9
b10000 :
#39250
b0 .
#39500
0!
#40000
1!
#40050
b11000 #
b10100 9
b10100 :
b10100 8
b10000 6
b0 1
b0 >
b0 0
b0 A
#40200
b10100100001011111111111111011 $
b10100100001011111111111111011 <
#40500
0!
#41000
1!
#41050
b11100 #
b10100 6
b11000 8
b10100100001011111111111111011 7
b11000 9
b11000 :
#41150
b11111111111111111111111111101100 ,
b101 *
b100 &
b100 ?
b101 %
b101 @
b11111 )
b1111111111111011 +
#41200
b100000 $
b100000 <
#41300
b100 (
b100 D
b1 '
b1 C
#41500
0!
#42000
1!
#42050
b100000 #
b11100 9
b11100 :
b100000 7
b11100 8
b101 2
b100 4
b1 5
b11111 3
b100 6
#42150
b0 ,
b0 *
b0 &
b0 ?
b0 %
b0 @
b0 )
b100000 +
#42250
b100 #
1-
b101 .
#42300
b0 (
b0 D
b0 '
b0 C
#42500
0!
#43000
1!
#43050
0B
b11100 #
b101 /
b11100 6
b0 3
b0 5
b0 4
b0 2
b100000 8
b100 9
b100 :
#43200
b101000010010100000100000 $
b101000010010100000100000 <
#43250
b1000 #
0-
b0 .
#43500
0!
#44000
1!
#44050
1B
b1100 #
b1000 9
b1000 :
b101000010010100000100000 7
b1000 8
b100000 6
b0 /
#44150
b101 &
b101 ?
b1 %
b1 @
b101 )
b10100000100000 +
#44200
b100000 $
b100000 <
#44300
b1 (
b1 D
b1 '
b1 C
#44500
0!
#45000
1!
#45050
b10000 #
b1000 6
b101 3
b1 5
b1 4
b1100 8
b100000 7
b1100 9
b1100 :
#45150
b0 &
b0 ?
b0 %
b0 @
b0 )
b100000 +
#45250
b10 .
#45300
b0 (
b0 D
b0 '
b0 C
#45500
0!
#46000
1!
#46050
b10100 #
b10000 9
b10000 :
b10000 8
b0 4
b0 5
b0 3
b1100 6
b10 1
b10 >
b101 0
b101 A
#46250
b0 .
#46500
0!
#47000
1!
#47050
b11000 #
b0 0
b0 A
b0 1
b0 >
b10000 6
b10100 8
b10100 9
b10100 :
#47200
b10100100001011111111111111011 $
b10100100001011111111111111011 <
#47500
0!
#48000
1!
#48050
b11100 #
b11000 9
b11000 :
b10100100001011111111111111011 7
b11000 8
b10100 6
#48150
b11111111111111111111111111101100 ,
b101 *
b100 &
b100 ?
b101 %
b101 @
b11111 )
b1111111111111011 +
#48200
b100000 $
b100000 <
#48300
b100 (
b100 D
b10 '
b10 C
#48500
0!
#49000
1!
#49050
b100000 #
b100 6
b11111 3
b10 5
b100 4
b101 2
b11100 8
b100000 7
b11100 9
b11100 :
#49150
b0 ,
b0 *
b0 &
b0 ?
b0 %
b0 @
b0 )
b100000 +
#49250
b100 #
1-
b110 .
#49300
b0 (
b0 D
b0 '
b0 C
#49500
0!
#50000
1!
#50050
0B
b11100 #
b100 9
b100 :
b100000 8
b0 2
b0 4
b0 5
b0 3
b11100 6
b101 /
#50200
b101000010010100000100000 $
b101000010010100000100000 <
#50250
b1000 #
0-
b0 .
#50500
0!
#51000
1!
#51050
1B
b1100 #
b0 /
b100000 6
b1000 8
b101000010010100000100000 7
b1000 9
b1000 :
#51150
b101 &
b101 ?
b1 %
b1 @
b101 )
b10100000100000 +
#51200
b100000 $
b100000 <
#51300
b10 (
b10 D
b1 '
b1 C
#51500
0!
#52000
1!
#52050
b10000 #
b1100 9
b1100 :
b100000 7
b1100 8
b10 4
b1 5
b101 3
b1000 6
#52150
b0 &
b0 ?
b0 %
b0 @
b0 )
b100000 +
#52250
b11 .
#52300
b0 (
b0 D
b0 '
b0 C
#52500
0!
#53000
1!
#53050
b10100 #
b101 0
b101 A
b11 1
b11 >
b1100 6
b0 3
b0 5
b0 4
b10000 8
b10000 9
b10000 :
#53250
b0 .
#53500
0!
#54000
1!
#54050
b11000 #
b10100 9
b10100 :
b10100 8
b10000 6
b0 1
b0 >
b0 0
b0 A
#54200
b10100100001011111111111111011 $
b10100100001011111111111111011 <
#54500
0!
#55000
1!
#55050
b11100 #
b10100 6
b11000 8
b10100100001011111111111111011 7
b11000 9
b11000 :
#55150
b11111111111111111111111111101100 ,
b101 *
b100 &
b100 ?
b101 %
b101 @
b11111 )
b1111111111111011 +
#55200
b100000 $
b100000 <
#55300
b100 (
b100 D
b11 '
b11 C
#55500
0!
#56000
1!
#56050
b100000 #
b11100 9
b11100 :
b100000 7
b11100 8
b101 2
b100 4
b11 5
b11111 3
b100 6
#56150
b0 ,
b0 *
b0 &
b0 ?
b0 %
b0 @
b0 )
b100000 +
#56250
b100 #
1-
b111 .
#56300
b0 (
b0 D
b0 '
b0 C
#56500
0!
#57000
1!
#57050
0B
b11100 #
b101 /
b11100 6
b0 3
b0 5
b0 4
b0 2
b100000 8
b100 9
b100 :
#57200
b101000010010100000100000 $
b101000010010100000100000 <
#57250
b1000 #
0-
b0 .
#57500
0!
#58000
1!
#58050
1B
b1100 #
b1000 9
b1000 :
b101000010010100000100000 7
b1000 8
b100000 6
b0 /
#58150
b101 &
b101 ?
b1 %
b1 @
b101 )
b10100000100000 +
#58200
b100000 $
b100000 <
#58300
b11 (
b11 D
b1 '
b1 C
#58500
0!
#59000
1!
#59050
b10000 #
b1000 6
b101 3
b1 5
b11 4
b1100 8
b100000 7
b1100 9
b1100 :
#59150
b0 &
b0 ?
b0 %
b0 @
b0 )
b100000 +
#59250
b100 .
#59300
b0 (
b0 D
b0 '
b0 C
#59500
0!
#60000
1!
#60050
b10100 #
b10000 9
b10000 :
b10000 8
b0 4
b0 5
b0 3
b1100 6
b100 1
b100 >
b101 0
b101 A
#60250
b0 .
#60500
0!
#61000
1!
#61050
b11000 #
b0 0
b0 A
b0 1
b0 >
b10000 6
b10100 8
b10100 9
b10100 :
#61200
b10100100001011111111111111011 $
b10100100001011111111111111011 <
#61500
0!
#62000
1!
#62050
b11100 #
b11000 9
b11000 :
b10100100001011111111111111011 7
b11000 8
b10100 6
#62150
b11111111111111111111111111101100 ,
b101 *
b100 &
b100 ?
b101 %
b101 @
b11111 )
b1111111111111011 +
#62200
b100000 $
b100000 <
#62300
b100 (
b100 D
b100 '
b100 C
#62500
0!
#63000
1!
#63050
b100000 #
b100 6
b11111 3
b100 5
b100 4
b101 2
b11100 8
b100000 7
b11100 9
b11100 :
#63150
b0 ,
b0 *
b0 &
b0 ?
b0 %
b0 @
b0 )
b100000 +
#63250
b1000 .
#63300
b0 (
b0 D
b0 '
b0 C
#63500
0!
#64000
1!
#64050
0B
b100100 #
b100000 9
b100000 :
b100000 8
b0 2
b0 4
b0 5
b0 3
b11100 6
b101 /
#64200
b10100000100000 $
b10100000100000 <
#64250
b0 .
#64500
0!
#65000
1!
#65050
1B
b101000 #
b0 /
b100000 6
b100100 8
b10100000100000 7
b100100 9
b100100 :
#65150
b101 )
b10100000100000 +
#65200
b100000 $
b100000 <
#65500
0!
#66000
1!
#66050
b101100 #
b101000 9
b101000 :
b100000 7
b101000 8
b101 3
b100100 6
#66150
b0 )
b100000 +
#66500
0!
#67000
1!
#67050
b110000 #
b101 0
b101 A
b101000 6
b0 3
b101100 8
b101100 9
b101100 :
#67200
b10100010000001111111111110101 $
b10100010000001111111111110101 <
#67500
0!
#68000
1!
#68050
b110100 #
b110000 9
b110000 :
b10100010000001111111111110101 7
b110000 8
b101100 6
b0 0
b0 A
#68150
b11111111111111111111111111010100 ,
b101 *
b10 &
b10 ?
b11111 )
b1111111111110101 +
#68200
b100000 $
b100000 <
#68300
b10110 (
b10110 D
#68500
0!
#69000
1!
#69050
b111000 #
b100 6
b11111 3
b10110 4
b101 2
b110100 8
b100000 7
b110100 9
b110100 :
#69150
b0 ,
b0 *
b0 &
b0 ?
b0 )
b100000 +
#69250
b100 #
1-
b10110 .
#69300
b0 (
b0 D
#69500
0!
#70000
1!
#70050
0B
b110100 #
b100 9
b100 :
b111000 8
b0 2
b0 4
b0 3
b110100 6
b101 /
#70200
b101000010010100000100000 $
b101000010010100000100000 <
#70250
b1000 #
0-
b0 .
#70500
0!
#71000
1!
#71050
1B
b1100 #
b0 /
b111000 6
b1000 8
b101000010010100000100000 7
b1000 9
b1000 :
#71150
b101 &
b101 ?
b1 %
b1 @
b101 )
b10100000100000 +
#71200
b100000 $
b100000 <
#71300
b1 '
b1 C
#71500
0!
#72000
1!
#72050
b10000 #
b1100 9
b1100 :
b100000 7
b1100 8
b1 5
b101 3
b1000 6
#72150
b0 &
b0 ?
b0 %
b0 @
b0 )
b100000 +
#72250
b1 .
#72300
b0 '
b0 C
#72500
0!
#73000
1!
#73050
b10100 #
b101 0
b101 A
b1 1
b1 >
b1100 6
b0 3
b0 5
b10000 8
b10000 9
b10000 :
#73250
b0 .
#73500
0!
#74000
1!
#74050
b11000 #
b10100 9
b10100 :
b10100 8
b10000 6
b0 1
b0 >
b0 0
b0 A
#74200
b10100100001011111111111111011 $
b10100100001011111111111111011 <
#74500
0!
#75000
1!
#75050
b11100 #
b10100 6
b11000 8
b10100100001011111111111111011 7
b11000 9
b11000 :
#75150
b11111111111111111111111111101100 ,
b101 *
b100 &
b100 ?
b101 %
b101 @
b11111 )
b1111111111111011 +
#75200
b100000 $
b100000 <
#75300
b100 (
b100 D
b1 '
b1 C
#75500
0!
#76000
1!
#76050
b100000 #
b11100 9
b11100 :
b100000 7
b11100 8
b101 2
b100 4
b1 5
b11111 3
b100 6
#76150
b0 ,
b0 *
b0 &
b0 ?
b0 %
b0 @
b0 )
b100000 +
#76250
b100 #
1-
b101 .
#76300
b0 (
b0 D
b0 '
b0 C
#76500
0!
#77000
1!
#77050
0B
b11100 #
b101 /
b11100 6
b0 3
b0 5
b0 4
b0 2
b100000 8
b100 9
b100 :
#77200
b101000010010100000100000 $
b101000010010100000100000 <
#77250
b1000 #
0-
b0 .
#77500
0!
#78000
1!
#78050
1B
b1100 #
b1000 9
b1000 :
b101000010010100000100000 7
b1000 8
b100000 6
b0 /
#78150
b101 &
b101 ?
b1 %
b1 @
b101 )
b10100000100000 +
#78200
b100000 $
b100000 <
#78300
b1 (
b1 D
b1 '
b1 C
#78500
0!
#79000
1!
#79050
b10000 #
b1000 6
b101 3
b1 5
b1 4
b1100 8
b100000 7
b1100 9
b1100 :
#79150
b0 &
b0 ?
b0 %
b0 @
b0 )
b100000 +
#79250
b10 .
#79300
b0 (
b0 D
b0 '
b0 C
#79500
0!
#80000
1!
#80050
b10100 #
b10000 9
b10000 :
b10000 8
b0 4
b0 5
b0 3
b1100 6
b10 1
b10 >
b101 0
b101 A
#80250
b0 .
#80500
0!
#81000
1!
#81050
b11000 #
b0 0
b0 A
b0 1
b0 >
b10000 6
b10100 8
b10100 9
b10100 :
#81200
b10100100001011111111111111011 $
b10100100001011111111111111011 <
#81500
0!
#82000
1!
#82050
b11100 #
b11000 9
b11000 :
b10100100001011111111111111011 7
b11000 8
b10100 6
#82150
b11111111111111111111111111101100 ,
b101 *
b100 &
b100 ?
b101 %
b101 @
b11111 )
b1111111111111011 +
#82200
b100000 $
b100000 <
#82300
b100 (
b100 D
b10 '
b10 C
#82500
0!
#83000
1!
#83050
b100000 #
b100 6
b11111 3
b10 5
b100 4
b101 2
b11100 8
b100000 7
b11100 9
b11100 :
